{
    "type": "FeatureCollection",
    "features": [
        {
            "type": "Feature",
            "properties": {},
            "geometry": {
                "type": "Polygon",
                "coordinates": [
                    [
                        [
                            1.442645,
                            43.607119
                        ],
                        [
                            1.442645,
                            43.611622
                        ],
                        [
                            1.449127,
                            43.611622
                        ],
                        [
                            1.449127,
                            43.607119
                        ],
                        [
                            1.442645,
                            43.607119
                        ]
                    ]
                ]
            }
        }
    ],
    "name": "1",
    "description": "1",
    "level": 0
}